dynamo2m/__init__.py
dynamo2m/dynamo2warp.py
dynamo2m/relion_star_downgrade.py
dynamo2m/utils.py
dynamo2m/version.py
dynamo2m/warp2dynamo.py
dynamo2m-0.2.2.dist-info/LICENSE.txt
dynamo2m-0.2.2.dist-info/METADATA
dynamo2m-0.2.2.dist-info/WHEEL
dynamo2m-0.2.2.dist-info/entry_points.txt
dynamo2m-0.2.2.dist-info/top_level.txt
dynamo2m-0.2.2.dist-info/RECORD
